MANIFEST.in
setup.py
debian/changelog
debian/compat
debian/control
debian/rules
lib/cr_hydra/__init__.py
lib/cr_hydra/settings.py
src/crh_add.py
src/crh_get_file.py
src/crh_retrieve.py
src/crh_worker.py
src/cr_hydra.egg-info/PKG-INFO
src/cr_hydra.egg-info/SOURCES.txt
src/cr_hydra.egg-info/dependency_links.txt
src/cr_hydra.egg-info/entry_points.txt
src/cr_hydra.egg-info/requires.txt
src/cr_hydra.egg-info/top_level.txt