Metadata-Version: 2.1
Name: cr-hydra
Version: 0.2.0
Summary: CRHydra - distributed CRTomo computing
Author: Maximilian Weigand
Author-email: mweigand@geo.uni-bonn.de
License: MIT
